setup.py
flask_frink/__init__.py
flask_frink/connection.py
flask_frink/datastore.py
flask_frink.egg-info/PKG-INFO
flask_frink.egg-info/SOURCES.txt
flask_frink.egg-info/dependency_links.txt
flask_frink.egg-info/pbr.json
flask_frink.egg-info/requires.txt
flask_frink.egg-info/top_level.txt