Metadata-Version: 1.1
Name: flask-frink
Version: 0.0.1
Summary: Add Flask-Security datastore functionality to Frink.
Home-page: https://github.com/hactar-is/flask-frink
Author: Hactar
Author-email: systems@hactar.is
License: UNKNOWN
Platform: UNKNOWN
Classifier: Development Status :: 2 - Pre-Alpha
Classifier: Programming Language :: Python
Classifier: Programming Language :: Python :: 2
Classifier: Programming Language :: Python :: 2.7
Classifier: Programming Language :: Python :: 3
Classifier: Programming Language :: Python :: 3.4
